LICENSE
README.rst
setup.cfg
setup.py
i3_workscreen.egg-info/PKG-INFO
i3_workscreen.egg-info/SOURCES.txt
i3_workscreen.egg-info/dependency_links.txt
i3_workscreen.egg-info/entry_points.txt
i3_workscreen.egg-info/requires.txt
i3_workscreen.egg-info/top_level.txt
i3workscreen/__init__.py
i3workscreen/i3workscreen.py
i3workscreen/validationschema.py