Metadata-Version: 2.1
Name: i3-workscreen
Version: 1.0.1
Summary: i3wm - assign workspaces to correct display outputs based on multi-scenario multi-monitor configuration
Home-page: https://github.com/fogine/i3-workscreen
Author: fogine
License: MIT
Download-URL: https://github.com/fogine/i3-workscreen/archive/1.0.1.tar.gz
Project-URL: Bug Reports, https://github.com/pypa/sampleproject/issues
Project-URL: Source, https://github.com/fogine/i3-workscreen
Keywords: i3 workspace monitor
Platform: UNKNOWN
Classifier: Development Status :: 3 - Alpha
Classifier: Intended Audience :: End Users/Desktop
Classifier: Operating System :: POSIX :: Linux
Classifier: Topic :: Desktop Environment :: Window Managers
Classifier: License :: OSI Approved :: MIT License
Classifier: Programming Language :: Python :: 3.6
Requires-Python: >=3.5.0
License-File: LICENSE
